constrata/__init__.py
constrata/binary_struct.py
constrata/byte_order.py
constrata/exceptions.py
constrata/field_types/__init__.py
constrata/field_types/primitive_types.py
constrata/field_types/type_info.py
constrata/fields.py
constrata/metacls.py
constrata/metadata.py
constrata/streams/__init__.py
constrata/streams/base.py
constrata/streams/bits.py
constrata/streams/reader.py
constrata/streams/writer.py
constrata/utilities.py
constrata-1.2.0.dist-info/LICENSE
constrata-1.2.0.dist-info/METADATA
constrata-1.2.0.dist-info/WHEEL
constrata-1.2.0.dist-info/RECORD
