Metadata-Version: 2.3
Name: constrata
Version: 1.2.0
Summary: Binary struct reading/writing Python library based on dataclass schemas
License: MIT
Author: Scott Mooney
Author-email: grimrukh@gmail.com
Requires-Python: >=3.11,<4.0
Classifier: License :: OSI Approved :: MIT License
Classifier: Operating System :: OS Independent
Classifier: Programming Language :: Python :: 3
Classifier: Programming Language :: Python :: 3.11
Classifier: Programming Language :: Python :: 3.12
Classifier: Programming Language :: Python :: 3.13
Project-URL: Homepage, https://github.com/Grimrukh/constrata
Project-URL: Repository, https://github.com/Grimrukh/constrata
